webexpythonsdk/__init__.py
webexpythonsdk/_metadata.py
webexpythonsdk/api/__init__.py
webexpythonsdk/api/access_tokens.py
webexpythonsdk/api/admin_audit_events.py
webexpythonsdk/api/attachment_actions.py
webexpythonsdk/api/events.py
webexpythonsdk/api/guest_issuer.py
webexpythonsdk/api/licenses.py
webexpythonsdk/api/meeting_invitees.py
webexpythonsdk/api/meeting_registrants.py
webexpythonsdk/api/meeting_templates.py
webexpythonsdk/api/meetings.py
webexpythonsdk/api/memberships.py
webexpythonsdk/api/messages.py
webexpythonsdk/api/organizations.py
webexpythonsdk/api/people.py
webexpythonsdk/api/recordings.py
webexpythonsdk/api/roles.py
webexpythonsdk/api/room_tabs.py
webexpythonsdk/api/rooms.py
webexpythonsdk/api/team_memberships.py
webexpythonsdk/api/teams.py
webexpythonsdk/api/webhooks.py
webexpythonsdk/config.py
webexpythonsdk/environment.py
webexpythonsdk/exceptions.py
webexpythonsdk/generator_containers.py
webexpythonsdk/models/__init__.py
webexpythonsdk/models/cards/__init__.py
webexpythonsdk/models/cards/actions.py
webexpythonsdk/models/cards/adaptive_card_component.py
webexpythonsdk/models/cards/card_elements.py
webexpythonsdk/models/cards/cards.py
webexpythonsdk/models/cards/containers.py
webexpythonsdk/models/cards/inputs.py
webexpythonsdk/models/cards/options.py
webexpythonsdk/models/cards/types.py
webexpythonsdk/models/cards/utils.py
webexpythonsdk/models/dictionary.py
webexpythonsdk/models/immutable.py
webexpythonsdk/models/mixins/__init__.py
webexpythonsdk/models/mixins/access_token.py
webexpythonsdk/models/mixins/admin_audit_event.py
webexpythonsdk/models/mixins/attachment_action.py
webexpythonsdk/models/mixins/event.py
webexpythonsdk/models/mixins/guest_issuer_token.py
webexpythonsdk/models/mixins/license.py
webexpythonsdk/models/mixins/meeting_invitees.py
webexpythonsdk/models/mixins/meeting_registrants.py
webexpythonsdk/models/mixins/meeting_templates.py
webexpythonsdk/models/mixins/meetings.py
webexpythonsdk/models/mixins/membership.py
webexpythonsdk-2.0.5.dist-info/LICENSE
webexpythonsdk-2.0.5.dist-info/METADATA
webexpythonsdk-2.0.5.dist-info/WHEEL
webexpythonsdk-2.0.5.dist-info/RECORD
