Metadata-Version: 2.3
Name: webexpythonsdk
Version: 2.0.5
Summary: Work with the Webex APIs in native Python!
License: MIT
Keywords: cisco,webex,api,sdk,python
Author: Chris Lunsford
Author-email: cm@lunsford.io
Requires-Python: >=3.10,<4.0
Classifier: Development Status :: 5 - Production/Stable
Classifier: Intended Audience :: Developers
Classifier: Intended Audience :: Information Technology
Classifier: Intended Audience :: System Administrators
Classifier: Intended Audience :: Telecommunications Industry
Classifier: License :: OSI Approved :: MIT License
Classifier: Natural Language :: English
Classifier: Programming Language :: Python :: 3
Classifier: Programming Language :: Python :: 3.10
Classifier: Programming Language :: Python :: 3.11
Classifier: Programming Language :: Python :: 3.12
Classifier: Programming Language :: Python :: 3.13
Classifier: Programming Language :: Python :: Implementation :: CPython
Classifier: Topic :: Communications
Classifier: Topic :: Communications :: Chat
Classifier: Topic :: Communications :: Conferencing
Classifier: Topic :: Software Development :: Libraries :: Python Modules
Requires-Dist: PyJWT (>=2.8.0,<3.0.0)
Requires-Dist: requests (>=2.32.3,<3.0.0)
Requires-Dist: requests-toolbelt (>=1.0.0,<2.0.0)
Project-URL: Documentation, https://webexcommunity.github.io/WebexPythonSDK
Project-URL: Homepage, https://github.com/WebexCommunity/WebexPythonSDK
Project-URL: Repository, https://github.com/WebexCommunity/WebexPythonSDK
